LICENSE.rst
README.md
setup.cfg
setup.py
src/damp11113/DSP.py
src/damp11113/PyserHTTP.py
src/damp11113/__init__.py
src/damp11113/codec.py
src/damp11113/convert.py
src/damp11113/file.py
src/damp11113/format.py
src/damp11113/imageps.py
src/damp11113/info.py
src/damp11113/logic.py
src/damp11113/media.py
src/damp11113/minecraft.py
src/damp11113/network.py
src/damp11113/plusmata.py
src/damp11113/processbar.py
src/damp11113/pywindows.py
src/damp11113/randoms.py
src/damp11113/timeline.py
src/damp11113/utils.py
src/damp11113.egg-info/PKG-INFO
src/damp11113.egg-info/SOURCES.txt
src/damp11113.egg-info/dependency_links.txt
src/damp11113.egg-info/requires.txt
src/damp11113.egg-info/top_level.txt
src/damp11113/OPFONMW/StepperLib.py
src/damp11113/OPFONMW/__init__.py
src/damp11113/OPFONMW/adpcm.py
src/damp11113/OPFONMW/dearpygui_animate.py
src/damp11113/PyqtWidget/LCD.py
src/damp11113/PyqtWidget/__init__.py